{
  "id": "tctv-631d58e3-99a3-4aae-9d70-2156f8c9f08a",
  "title": "Execute basic queries",
  "description": "Given a database with tables, when I call execute() with where, pk, fields, or limit directives, it should return matching records with correct field projection and limits. Non-existent table raises an error (fail fast). Non-existent GSI name raises an error. Spec: features/query/execute_basic.feature",
  "type": "story",
  "status": "open",
  "priority": 2,
  "assignee": null,
  "creator": null,
  "parent": "tctv-ab37b375-adfd-44f4-b71c-2bb7658a476e",
  "labels": [],
  "dependencies": [],
  "comments": [],
  "created_at": "2026-02-21T16:46:42.964912Z",
  "updated_at": "2026-02-21T17:07:56.993709Z",
  "closed_at": null,
  "custom": {}
}